{
	"description": "项目配置文件。",
	"setting": {
		"urlCheck": false,
		"es6": true,
		"postcss": true,
		"minified": true,
		"newFeature": true
	},
	"compileType": "miniprogram",
	"libVersion": "1.5.4",
	"appid": "wx84ff824de3e1f6b6",
	"projectname": "%E6%96%B0%E9%98%85",
	"condition": {
		"search": {
			"current": -1,
			"list": []
		},
		"conversation": {
			"current": -1,
			"list": []
		},
		"game": {
			"current": -1,
			"list": []
		},
		"miniprogram": {
			"current": 4,
			"list": [
				{
					"id": 0,
					"name": "info",
					"pathName": "pages/info/info",
					"query": "project_id=P61508596944&id=86",
					"scene": "1011"
				},
				{
					"id": 1,
					"name": "info",
					"pathName": "pages/info/info",
					"query": "scene=code%3d7b3f9ae0a1e0d08c",
					"scene": "1011"
				},
				{
					"id": 2,
					"name": "info",
					"pathName": "pages/info/info",
					"query": "project_id=P1661511345288&id=801",
					"scene": "1011"
				},
				{
					"id": -1,
					"name": "notice",
					"pathName": "pages/notice/notice",
					"query": ""
				},
				{
					"id": -1,
					"name": "info_new",
					"pathName": "pages/info/info",
					"query": "url=http://video.uxinyue.com/23d3fe67ae094c62bfe20dbb4d1d0725/2a4453c5c810440c817640337f6fbb51-a5b7d8911cc7d347a9c9dd7e9b1d521b.mp4&name=3F7CAE54-15F29423761-1379-0064-227-94904.mp4.mp4&id=1034&username=stone1645&createTime=77天前&coverImg=http://xinyue-1253999721.cossh.myqcloud.com/cover_img/1omuDR8yGLfXH0iMoWN2nOsFLQomeyHQJaUUGXwR.jpg&project_id=P2571513772781 ",
					"scene": "1011"
				}
			]
		}
	}
}